{
  "classification": {
    "luckClass": "expected_loss",
    "scoreMargin": -2,
    "segments": [
      "delivered",
      "task90_reached",
      "mid_trail",
      "weather_hit",
      "opp_delivered"
    ]
  },
  "clientVersion": "iter31",
  "decisionTimeline": [
    {
      "detail": "CLEAR S06 cost 1",
      "event": "BREAKTHROUGH",
      "frame": 1
    },
    {
      "detail": "T_003",
      "event": "TASK_CLAIM",
      "frame": 185
    },
    {
      "detail": "T_005",
      "event": "TASK_CLAIM",
      "frame": 189
    },
    {
      "detail": "T_009",
      "event": "TASK_CLAIM",
      "frame": 193
    },
    {
      "detail": "SHORT_HORSE",
      "event": "USE_HORSE",
      "frame": 200
    },
    {
      "detail": "T_008",
      "event": "TASK_CLAIM",
      "frame": 269
    },
    {
      "detail": "T_011",
      "event": "TASK_CLAIM",
      "frame": 273
    },
    {
      "detail": "fresh=77.0",
      "event": "USE_ICE",
      "frame": 327
    },
    {
      "detail": "RUSH_PROTECT",
      "event": "RUSH_TACTIC",
      "frame": 426
    }
  ],
  "delivery": {
    "me": {
      "frame": 444,
      "freshness": 81.36,
      "goodFruit": 97,
      "verifyFrame": 430
    },
    "opp": {
      "frame": 475,
      "verifyFrame": 461
    },
    "rushTriggerFrame": 426
  },
  "durationRound": 600,
  "failures": {
    "canAffordBlocked": [],
    "decisionTimeouts": 0,
    "invalidActions": 0,
    "rejected": [],
    "waitingStuck": []
  },
  "finalScore": {
    "me": {
      "bounty": 0,
      "delivery": 240,
      "freshness": 146,
      "goodFruit": 174,
      "penalty": 0,
      "task": 180,
      "time": 18,
      "total": 758
    },
    "opp": {
      "bounty": 0,
      "delivery": 240,
      "freshness": 148,
      "goodFruit": 178,
      "penalty": 0,
      "task": 180,
      "time": 14,
      "total": 760
    }
  },
  "matchId": "match_20260704_191739_976_2613_vs_2696_611e69d5",
  "opponentInteraction": {
    "bounties": [],
    "myGuards": [],
    "oppGuards": [],
    "windows": []
  },
  "outcome": "LOSS",
  "playerId": 2696,
  "projection": {
    "actualMyScore": 758,
    "confidence": {
      "max": 0.74,
      "median": 0.52,
      "min": 0.3
    },
    "error": -4,
    "modeSwitches": [],
    "oppActualDeliver": 475,
    "oppEtaPredictedDeliver": 475,
    "projectedMyScore": 754
  },
  "resources": {
    "horseUsed": "SHORT_HORSE@200",
    "iceUsed": [
      {
        "frame": 327,
        "freshnessBefore": 76.99
      }
    ],
    "rushTactic": {
      "frame": 426,
      "type": "RUSH_PROTECT"
    }
  },
  "schemaVersion": 2,
  "seed": null,
  "source": "platform",
  "tasks": {
    "me": {
      "base": 150,
      "claimed": [
        {
          "detourExtra": null,
          "frame": 185,
          "node": "S08",
          "template": null
        },
        {
          "detourExtra": null,
          "frame": 189,
          "node": "S08",
          "template": null
        },
        {
          "detourExtra": null,
          "frame": 193,
          "node": "S08",
          "template": null
        },
        {
          "detourExtra": null,
          "frame": 269,
          "node": "S10",
          "template": null
        },
        {
          "detourExtra": null,
          "frame": 273,
          "node": "S10",
          "template": null
        }
      ],
      "milestones": [
        60,
        90,
        110
      ]
    },
    "missedReachable90": null,
    "opp": {
      "base": 180,
      "claimed": [
        {
          "frame": 85,
          "taskScore": 30
        },
        {
          "frame": 166,
          "taskScore": 60
        },
        {
          "frame": 170,
          "taskScore": 90
        },
        {
          "frame": 239,
          "taskScore": 105
        },
        {
          "frame": 299,
          "taskScore": 135
        },
        {
          "frame": 353,
          "taskScore": 165
        },
        {
          "frame": 357,
          "taskScore": 180
        }
      ],
      "milestones": [
        60,
        90,
        110
      ]
    }
  },
  "teamId": "BLUE",
  "trajectory": {
    "freshness": {
      "end": 81.36,
      "min": 76.99,
      "start": 100
    },
    "goodFruit": {
      "badCrossings": [
        90,
        80
      ],
      "end": 97,
      "start": 100
    },
    "opponent": {
      "badFruitEnd": 1,
      "frames": [
        {
          "b": 0,
          "ga": 4,
          "mp": 0,
          "n": "S01",
          "r": 1,
          "s": "IDLE",
          "ts": 0
        },
        {
          "b": 0,
          "ga": 4,
          "mp": 0.02,
          "n": "S01",
          "nx": "S02",
          "r": 2,
          "s": "MOVING",
          "ts": 0
        },
        {
          "b": 0,
          "ga": 4,
          "mp": 0.05,
          "n": "S01",
          "nx": "S02",
          "r": 3,
          "s": "MOVING",
          "ts": 0
        },
        {
          "b": 0,
          "ga": 4,
          "mp": 0.07,
          "n": "S01",
          "nx": "S02",
          "r": 4,
          "s": "MOVING",
          "ts": 0
        },
        {
          "b": 0,
          "ga": 4,
          "mp": 0.1,
          "n": "S01",
          "nx": "S02",
          "r": 5,
          "s": "MOVING",
          "ts": 0
        },
        {
          "b": 0,
          "ga": 4,
          "mp": 0.12,
          "n": "S01",
          "nx": "S02",
          "r": 6,
          "s": "MOVING",
          "ts": 0
        },
        {
          "b": 0,
          "ga": 4,
          "mp": 0.14,
          "n": "S01",
          "nx": "S02",
          "r": 7,
          "s": "MOVING",
          "ts": 0
        },
        {
          "b": 0,
          "ga": 4,
          "mp": 0.17,
          "n": "S01",
          "nx": "S02",
          "r": 8,
          "s": "MOVING",
          "ts": 0
        },
        {
          "b": 0,
          "ga": 4,
          "mp": 0.19,
          "n": "S01",
          "nx": "S02",
          "r": 9,
          "s": "MOVING",
          "ts": 0
        },
        {
          "b": 0,
          "ga": 4,
          "mp": 0.22,
          "n": "S01",
          "nx": "S02",
          "r": 10,
          "s": "MOVING",
          "ts": 0
        },
        {
          "b": 0,
          "ga": 4,
          "mp": 0.24,
          "n": "S01",
          "nx": "S02",
          "r": 11,
          "s": "MOVING",
          "ts": 0
        },
        {
          "b": 0,
          "ga": 4,
          "mp": 0.27,
          "n": "S01",
          "nx": "S02",
          "r": 12,
          "s": "MOVING",
          "ts": 0
        },
        {
          "b": 1,
          "ga": 4,
          "mp": 0.22,
          "n": "S14",
          "nx": "S15",
          "r": 464,
          "s": "MOVING",
          "ts": 180,
          "vf": true
        },
        {
          "b": 1,
          "ga": 4,
          "mp": 0.29,
          "n": "S14",
          "nx": "S15",
          "r": 465,
          "s": "MOVING",
          "ts": 180,
          "vf": true
        },
        {
          "b": 1,
          "ga": 4,
          "mp": 0.36,
          "n": "S14",
          "nx": "S15",
          "r": 466,
          "s": "MOVING",
          "ts": 180,
          "vf": true
        },
        {
          "b": 1,
          "ga": 4,
          "mp": 0.43,
          "n": "S14",
          "nx": "S15",
          "r": 467,
          "s": "MOVING",
          "ts": 180,
          "vf": true
        },
        {
          "b": 1,
          "ga": 4,
          "mp": 0.51,
          "n": "S14",
          "nx": "S15",
          "r": 468,
          "s": "MOVING",
          "ts": 180,
          "vf": true
        },
        {
          "b": 1,
          "ga": 4,
          "mp": 0.58,
          "n": "S14",
          "nx": "S15",
          "r": 469,
          "s": "MOVING",
          "ts": 180,
          "vf": true
        },
        {
          "b": 1,
          "ga": 4,
          "mp": 0.65,
          "n": "S14",
          "nx": "S15",
          "r": 470,
          "s": "MOVING",
          "ts": 180,
          "vf": true
        },
        {
          "b": 1,
          "ga": 4,
          "mp": 0.72,
          "n": "S14",
          "nx": "S15",
          "r": 471,
          "s": "MOVING",
          "ts": 180,
          "vf": true
        },
        {
          "b": 1,
          "ga": 4,
          "mp": 0.8,
          "n": "S14",
          "nx": "S15",
          "r": 472,
          "s": "MOVING",
          "ts": 180,
          "vf": true
        },
        {
          "b": 1,
          "ga": 4,
          "mp": 0.87,
          "n": "S14",
          "nx": "S15",
          "r": 473,
          "s": "MOVING",
          "ts": 180,
          "vf": true
        },
        {
          "b": 1,
          "ga": 4,
          "mp": 0.94,
          "n": "S14",
          "nx": "S15",
          "r": 474,
          "s": "MOVING",
          "ts": 180,
          "vf": true
        },
        {
          "b": 1,
          "ga": 4,
          "mp": 0,
          "n": "S15",
          "r": 475,
          "s": "IDLE",
          "ts": 180,
          "vf": true
        }
      ],
      "freshnessEnd": 82.46,
      "freshnessMin": 82.46,
      "goodFruitEnd": 99,
      "iceUsed": [],
      "nodeEnd": "S15",
      "verifyFrame": 461
    }
  },
  "variant": "baseline"
}